Workbook
Name Slicer_Category: #N/A
Name Slicer_City: #N/A
Name Slicer_Months__Order_Date: #N/A

Sheet Sheet2
A3: Row Labels | B3: Sum of Net_Sales
A4: Accessories | B4: 41147
A5: Electronics | B5: 522697.88
A6: Furniture | B6: 339418.25
A7: Home & Decor | B7: 20504.125
A8: Stationery | B8: 3472.275
A9: Grand Total | B9: 927239.53

Sheet Sheet3
A3: Row Labels | B3: Sum of Net_Sales
A4: 2026 | B4: 927239.52
A5: Jan | B5: 282503.89
A6: Feb | B6: 384592.62
A7: Mar | B7: 260143.01
A8: Grand Total | B8: 927239.52

Sheet Sheet5
A3: Row Labels | B3: Sum of Net_Sales | C3: Sum of Gross_Sales
A4: Bengaluru | B4: 220984.76 | C4: 249527.75
A5: Delhi | B5: 204577.88 | C5: 221727.5
A6: Hyderabad | B6: 187694.75 | C6: 210417.5
A7: Kolkata | B7: 91621.762 | C7: 100060.75
A8: Mumbai | B8: 132952.88 | C8: 150095
A9: Ranchi | B9: 89407.5 | C9: 98690
A10: Grand Total | B10: 927239.52 | C10: 1030518.5

Sheet Sales_Data
A1: Order_ID | B1: Order_Date | C1: Customer_Name | D1: City | E1: Salesperson | F1: Product | G1: Category | H1: Quantity | I1: Unit_Price | J1: Discount_Percent | K1: Payment_Mode | L1: Order_Status | M1: Gross_Sales | N1: Net_Sales
A2: ORD001 | B2: 46069 | C2: Ananya Roy | D2: Ranchi | E2: Arjun | F2: Desk Lamp | G2: Home & Decor | H2: 4 | I2: 850 | J2: 20 | K2: Credit Card | L2: Delivered | M2: =SalesTable[[#This Row],[Quantity]]*SalesTable[[#This Row],[Unit_Price]] -> 3400 | N2: =SalesTable[[#This Row],[Gross_Sales]]*(1-SalesTable[[#This Row],[Discount_Percent]]/100) -> 2720
A3: ORD002 | B3: 46076 | C3: Ananya Roy | D3: Bengaluru | E3: Priya | F3: Laptop | G3: Electronics | H3: 1 | I3: 54600 | J3: 20 | K3: Debit Card | L3: Delivered | M3: =SalesTable[[#This Row],[Quantity]]*SalesTable[[#This Row],[Unit_Price]] -> 54600 | N3: =SalesTable[[#This Row],[Gross_Sales]]*(1-SalesTable[[#This Row],[Discount_Percent]]/100) -> 43680
A4: ORD003 | B4: 46048 | C4: Priya Singh | D4: Hyderabad | E4: Neha | F4: Desk Lamp | G4: Home & Decor | H4: 1 | I4: 850 | J4: 15 | K4: Cash | L4: Delivered | M4: =SalesTable[[#This Row],[Quantity]]*SalesTable[[#This Row],[Unit_Price]] -> 850 | N4: =SalesTable[[#This Row],[Gross_Sales]]*(1-SalesTable[[#This Row],[Discount_Percent]]/100) -> 722.5
A5: ORD004 | B5: 46062 | C5: Sana Khan | D5: Kolkata | E5: Neha | F5: Desk Lamp | G5: Home & Decor | H5: 1 | I5: 807.5 | J5: 10 | K5: Cash | L5: Pending | M5: =SalesTable[[#This Row],[Quantity]]*SalesTable[[#This Row],[Unit_Price]] -> 807.5 | N5: =SalesTable[[#This Row],[Gross_Sales]]*(1-SalesTable[[#This Row],[Discount_Percent]]/100) -> 726.75
A6: ORD005 | B6: 46078 | C6: Karan Gupta | D6: Bengaluru | E6: Ayesha | F6: Desk Lamp | G6: Home & Decor | H6: 3 | I6: 807.5 | J6: 20 | K6: Credit Card | L6: Delivered | M6: =SalesTable[[#This Row],[Quantity]]*SalesTable[[#This Row],[Unit_Price]] -> 2422.5 | N6: =SalesTable[[#This Row],[Gross_Sales]]*(1-SalesTable[[#This Row],[Discount_Percent]]/100) -> 1938
A7: ORD006 | B7: 46074 | C7: Rahul Khan | D7: Kolkata | E7: Neha | F7: Pen Pack | G7: Stationery | H7: 3 | I7: 95 | J7: 0 | K7: Cash | L7: Cancelled | M7: =SalesTable[[#This Row],[Quantity]]*SalesTable[[#This Row],[Unit_Price]] -> 285 | N7: =SalesTable[[#This Row],[Gross_Sales]]*(1-SalesTable[[#This Row],[Discount_Percent]]/100) -> 285
A8: ORD007 | B8: 46031 | C8: Ananya Roy | D8: Ranchi | E8: Arjun | F8: Desk | G8: Furniture | H8: 1 | I8: 12500 | J8: 15 | K8: Cash | L8: Delivered | M8: =SalesTable[[#This Row],[Quantity]]*SalesTable[[#This Row],[Unit_Price]] -> 12500 | N8: =SalesTable[[#This Row],[Gross_Sales]]*(1-SalesTable[[#This Row],[Discount_Percent]]/100) -> 10625
A9: ORD008 | B9: 46063 | C9: Priya Singh | D9: Delhi | E9: Ayesha | F9: Backpack | G9: Accessories | H9: 3 | I9: 1600 | J9: 15 | K9: Credit Card | L9: Delivered | M9: =SalesTable[[#This Row],[Quantity]]*SalesTable[[#This Row],[Unit_Price]] -> 4800 | N9: =SalesTable[[#This Row],[Gross_Sales]]*(1-SalesTable[[#This Row],[Discount_Percent]]/100) -> 4080
A10: ORD009 | B10: 46025 | C10: Vikash Kumar | D10: Hyderabad | E10: Priya | F10: Laptop | G10: Electronics | H10: 1 | I10: 52000 | J10: 10 | K10: UPI | L10: Delivered | M10: =SalesTable[[#This Row],[Quantity]]*SalesTable[[#This Row],[Unit_Price]] -> 52000 | N10: =SalesTable[[#This Row],[Gross_Sales]]*(1-SalesTable[[#This Row],[Discount_Percent]]/100) -> 46800
A11: ORD010 | B11: 46085 | C11: Amit Sharma | D11: Bengaluru | E11: Neha | F11: Office Chair | G11: Furniture | H11: 3 | I11: 7790 | J11: 15 | K11: Cash | L11: Pending | M11: =SalesTable[[#This Row],[Quantity]]*SalesTable[[#This Row],[Unit_Price]] -> 23370 | N11: =SalesTable[[#This Row],[Gross_Sales]]*(1-SalesTable[[#This Row],[Discount_Percent]]/100) -> 19864.5
A12: ORD011 | B12: 46048 | C12: Ananya Roy | D12: Ranchi | E12: Arjun | F12: Pen Pack | G12: Stationery | H12: 4 | I12: 100 | J12: 0 | K12: Cash | L12: Delivered | M12: =SalesTable[[#This Row],[Quantity]]*SalesTable[[#This Row],[Unit_Price]] -> 400 | N12: =SalesTable[[#This Row],[Gross_Sales]]*(1-SalesTable[[#This Row],[Discount_Percent]]/100) -> 400
A13: ORD012 | B13: 46063 | C13: Amit Sharma | D13: Ranchi | E13: Imran | F13: Desk Lamp | G13: Home & Decor | H13: 3 | I13: 850 | J13: 0 | K13: Credit Card | L13: Delivered | M13: =SalesTable[[#This Row],[Quantity]]*SalesTable[[#This Row],[Unit_Price]] -> 2550 | N13: =SalesTable[[#This Row],[Gross_Sales]]*(1-SalesTable[[#This Row],[Discount_Percent]]/100) -> 2550
... A101: ORD100 | B101: 46064 | C101: Riya Das | D101: Hyderabad | E101: Ayesha | F101: Monitor | G101: Electronics | H101: 2 | I101: 11500 | J101: 0 | K101: Debit Card | L101: Cancelled | M101: =SalesTable[[#This Row],[Quantity]]*SalesTable[[#This Row],[Unit_Price]] -> 23000 | N101: =SalesTable[[#This Row],[Gross_Sales]]*(1-SalesTable[[#This Row],[Discount_Percent]]/100) -> 23000

Sheet Dashboard
D3: RETAIL SALES DASHBOARD
B5: Total Net Sales | E5: Avg Order Value | H5: Total Orders | K5: Cancelled Orders
B6: =Summary!B3 -> 927239.52 | E6: =Summary!B5 -> 9272.3952 | H6: =Summary!B4 -> 100 | K6: =Summary!E11 -> 17
E38: Key Business Insights
E40: TOP CATEGORY | G40: ELECTRONICS
E41: BEST MONTH | G41: FEBURARY
E42: BEST CITY | G42: BENGALURU
E43: CANCELLATIONS RATE | G43: =Summary!E11/Summary!B4 -> 0.17

Sheet Summary
A1: Retail Sales Summary
A3: Total Net Sales | B3: =SUM(SalesTable[Net_Sales]) -> 927239.52
A4: Total Orders | B4: =COUNTA(SalesTable[Order_ID]) -> 100
A5: Average Order Value | B5: =AVERAGE(SalesTable[Net_Sales]) -> 9272.3952
A8: Category | B8: Net Sales | D8: Order Status | E8: Order Count
A9: Eletcronics | B9: =SUMIFS(SalesTable[Net_Sales],SalesTable[Category],A9) -> 0 | D9: Delivered | E9: =COUNTIFS(SalesTable[Order_Status],D9) -> 67
A10: Furniture | B10: =SUMIFS(SalesTable[Net_Sales],SalesTable[Category],A10) -> 339418.25 | D10: Pending | E10: =COUNTIFS(SalesTable[Order_Status],D10) -> 16
A11: Stationery | B11: =SUMIFS(SalesTable[Net_Sales],SalesTable[Category],A11) -> 3472.275 | D11: Cancelled | E11: =COUNTIFS(SalesTable[Order_Status],D11) -> 17
A12: Home | B12: =SUMIFS(SalesTable[Net_Sales],SalesTable[Category],A12) -> 0
A13: Decor | B13: =SUMIFS(SalesTable[Net_Sales],SalesTable[Category],A13) -> 0
A14: Accessories | B14: =SUMIFS(SalesTable[Net_Sales],SalesTable[Category],A14) -> 41147
